preprocessing/__init__.py
preprocessing/common/__init__.py
preprocessing/common/tensor_dataset.py
preprocessing/config/__init__.py
preprocessing/config/examples/air_passengers.yaml
preprocessing/downloader/__init__.py
preprocessing/downloader/gift_eval.py
preprocessing/downloader/huggingface.py
preprocessing/serialization/__init__.py
preprocessing/serialization/deserialize.py
preprocessing/serialization/serialize.py
preprocessing/synthetic/__init__.py
preprocessing/synthetic/linear_trend.py
preprocessing/transform/__init__.py
preprocessing/transform/batching_dataset.py
preprocessing/transform/combining_dataset.py
preprocessing/transform/concat_dataset.py
preprocessing/transform/dataset_builder.py
preprocessing/transform/probabilistic_mixing_dataset.py
preprocessing/transform/sliding_window_dataset.py
preprocessing/transform/transforming_dataset.py
preprocessing/transform/unbatching_dataset.py
ts_preprocessing-0.1.3.dist-info/METADATA
ts_preprocessing-0.1.3.dist-info/WHEEL
ts_preprocessing-0.1.3.dist-info/entry_points.txt
ts_preprocessing-0.1.3.dist-info/RECORD
