Metadata-Version: 2.3
Name: ts-preprocessing
Version: 0.1.3
Summary: A preprocessing library for foundation time series models
License: MIT
Keywords: time-series,preprocessing,ml
Author: Your Name
Author-email: your.email@example.com
Requires-Python: >=3.11,<4.0
Classifier: License :: OSI Approved :: MIT License
Classifier: Programming Language :: Python :: 3
Classifier: Programming Language :: Python :: 3.11
Classifier: Programming Language :: Python :: 3.12
Classifier: Programming Language :: Python :: 3.13
Requires-Dist: datasets (>=4.0.0,<5.0.0)
Requires-Dist: huggingface-hub (>=0.20.3)
Requires-Dist: hydra-core (>=1.3.2,<2.0.0)
Requires-Dist: omegaconf (>=2.3.0,<3.0.0)
Requires-Dist: torch (>=2.1.0,<3.0.0)
Requires-Dist: typer (>=0.9.0,<0.10.0)
Project-URL: Homepage, https://github.com/TimeBinFM/data
Project-URL: Repository, https://github.com/TimeBinFM/data
